data_scientists_util/__init__.py
data_scientists_util/helper.py
data_scientist_util_jaloeffe-0.0.3.dist-info/LICENSE
data_scientist_util_jaloeffe-0.0.3.dist-info/METADATA
data_scientist_util_jaloeffe-0.0.3.dist-info/WHEEL
data_scientist_util_jaloeffe-0.0.3.dist-info/top_level.txt
data_scientist_util_jaloeffe-0.0.3.dist-info/RECORD
